{
  "shown": [
    {
      "max_elev": 942, 
      "cumarea": 8963.815010609138, 
      "area": 5.68, 
      "num_lifts": 41, 
      "name": "Cerro Castor", 
      "source": "jsons/ski_area_elevations//south-america-latest.json", 
      "min_elev": 195, 
      "uid": "28254fee-65a2-4eb3-a149-f90f3bb987af"
    }, 
    {
      "max_elev": 940, 
      "uid": "5a92a74a-b2b5-4ff9-b3db-149846469cfb", 
      "area": 2.5, 
      "num_lifts": 6, 
      "source": "jsons/ski_area_elevations//asia-latest.json", 
      "min_elev": 257, 
      "cumarea": 8971.966714671173
    }, 
    {
      "max_elev": 942, 
      "uid": "023489ed-6f5f-4ca9-ab0e-34dd57afe493", 
      "area": 2.0, 
      "num_lifts": 2, 
      "source": "jsons/ski_area_elevations//europe-latest.json", 
      "min_elev": 677, 
      "cumarea": 8957.468293804784
    }, 
    {
      "max_elev": 940, 
      "uid": "40c1b752-f4cc-48b8-8298-04de20b61edd", 
      "area": 1.8900000000000001, 
      "num_lifts": 2, 
      "source": "jsons/ski_area_elevations//europe-latest.json", 
      "min_elev": 614, 
      "cumarea": 8969.050423939298
    }, 
    {
      "max_elev": 942, 
      "uid": "a0b71184-3f34-4076-b136-c5399706a0fe", 
      "area": 1.84, 
      "num_lifts": 1, 
      "source": "jsons/ski_area_elevations//europe-latest.json", 
      "min_elev": 825, 
      "cumarea": 8960.078059376405
    }, 
    {
      "max_elev": 941, 
      "uid": "8b80eb04-83c3-4e69-bf8c-ea4e26c82cf7", 
      "area": 1.82, 
      "num_lifts": 1, 
      "source": "jsons/ski_area_elevations//europe-latest.json", 
      "min_elev": 893, 
      "cumarea": 8966.413847110227
    }
  ], 
  "end_x": 8973.647918083592, 
  "num": 510, 
  "zoom": 10, 
  "start_x": 8956.086963253681
}