{
  "shown": [
    {
      "max_elev": 768, 
      "uid": "e3781ddf-2215-4423-9b24-7caefd6540e4", 
      "area": 1.9100000000000001, 
      "num_lifts": 2, 
      "source": "jsons/ski_area_elevations//north-america-latest.json", 
      "min_elev": 633, 
      "cumarea": 10612.024051037088
    }, 
    {
      "max_elev": 767, 
      "uid": "6a3d07a4-e6bb-4199-9ef9-fd3358d32be8", 
      "area": 1.87, 
      "num_lifts": 2, 
      "source": "jsons/ski_area_elevations//europe-latest.json", 
      "min_elev": 561, 
      "cumarea": 10614.649989467955
    }, 
    {
      "max_elev": 766, 
      "uid": "447ac8ef-88cc-47af-b890-4fd5ea7b14d2", 
      "area": 1.85, 
      "num_lifts": 1, 
      "source": "jsons/ski_area_elevations//europe-latest.json", 
      "min_elev": 599, 
      "cumarea": 10622.462817919175
    }, 
    {
      "max_elev": 767, 
      "uid": "4787e2b3-7e73-431e-9f5d-323807e9b8cb", 
      "area": 1.83, 
      "num_lifts": 1, 
      "source": "jsons/ski_area_elevations//europe-latest.json", 
      "min_elev": 641, 
      "cumarea": 10617.254305434808
    }, 
    {
      "max_elev": 767, 
      "uid": "378e4024-57df-44fd-93b7-b85a26fafb55", 
      "area": 1.81, 
      "num_lifts": 1, 
      "source": "jsons/ski_area_elevations//europe-latest.json", 
      "min_elev": 744, 
      "cumarea": 10619.847632280085
    }, 
    {
      "max_elev": 768, 
      "uid": "ed9b1f91-fd5d-4e30-90c0-ac95dda08e91", 
      "area": 1.8, 
      "num_lifts": 1, 
      "source": "jsons/ski_area_elevations//europe-latest.json", 
      "min_elev": 755, 
      "cumarea": 10609.37694779503
    }
  ], 
  "end_x": 10624.377672095057, 
  "num": 604, 
  "zoom": 10, 
  "start_x": 10606.816717265148
}