{
  "shown": [
    {
      "max_elev": 657, 
      "uid": "b8119554-0458-478b-93d8-474b96f4846c", 
      "area": 3.73, 
      "num_lifts": 40, 
      "source": "jsons/ski_area_elevations//north-america-latest.json", 
      "min_elev": 308, 
      "cumarea": 11745.80474250461
    }, 
    {
      "max_elev": 657, 
      "uid": "0e638ec4-2a56-4a02-89c1-ddd6cf63d9e8", 
      "area": 2.05, 
      "num_lifts": 15, 
      "source": "jsons/ski_area_elevations//europe-latest.json", 
      "min_elev": 549, 
      "cumarea": 11737.210739326758
    }, 
    {
      "max_elev": 653, 
      "uid": "ed33332d-75df-4c43-a775-21b294eca083", 
      "area": 1.98, 
      "num_lifts": 2, 
      "source": "jsons/ski_area_elevations//europe-latest.json", 
      "min_elev": 619, 
      "cumarea": 11764.161145414992
    }, 
    {
      "max_elev": 657, 
      "uid": "ba793948-75f9-4342-b9a4-51373f957ea1", 
      "area": 1.95, 
      "num_lifts": 4, 
      "source": "jsons/ski_area_elevations//europe-latest.json", 
      "min_elev": 533, 
      "cumarea": 11739.878568699334
    }, 
    {
      "max_elev": 654, 
      "uid": "0ead7191-3b83-4311-85f2-d1709b6453e8", 
      "area": 1.9100000000000001, 
      "num_lifts": 4, 
      "source": "jsons/ski_area_elevations//europe-latest.json", 
      "min_elev": 589, 
      "cumarea": 11761.478048570285
    }, 
    {
      "max_elev": 655, 
      "uid": "eeb0b8d3-c72a-4cc8-9a1f-772b52506f61", 
      "area": 1.8900000000000001, 
      "num_lifts": 2, 
      "source": "jsons/ski_area_elevations//asia-latest.json", 
      "min_elev": 554, 
      "cumarea": 11758.830945328227
    }, 
    {
      "max_elev": 658, 
      "uid": "6d9fe72a-e983-476d-93eb-009172466009", 
      "area": 1.85, 
      "num_lifts": 4, 
      "source": "jsons/ski_area_elevations//europe-latest.json", 
      "min_elev": 581, 
      "cumarea": 11734.492899533607
    }, 
    {
      "max_elev": 656, 
      "uid": "53a6d0cc-d5bf-439c-a848-eb4827ab841b", 
      "area": 1.85, 
      "num_lifts": 2, 
      "source": "jsons/ski_area_elevations//europe-latest.json", 
      "min_elev": 468, 
      "cumarea": 11748.4199281437
    }, 
    {
      "max_elev": 657, 
      "uid": "b3e2fc3b-6e2a-4c47-b8a4-9dc10f2b66d1", 
      "area": 1.84, 
      "num_lifts": 2, 
      "source": "jsons/ski_area_elevations//europe-latest.json", 
      "min_elev": 564, 
      "cumarea": 11742.488334270955
    }, 
    {
      "max_elev": 659, 
      "uid": "f98c38d2-129d-4564-8a49-370bd99c8328", 
      "area": 1.82, 
      "num_lifts": 1, 
      "source": "jsons/ski_area_elevations//europe-latest.json", 
      "min_elev": 528, 
      "cumarea": 11731.877713894517
    }
  ], 
  "end_x": 11765.839736039154, 
  "num": 334, 
  "zoom": 9, 
  "start_x": 11730.717826379336
}