{
  "shown": [
    {
      "max_elev": 883, 
      "uid": "49ba0056-c20f-4894-b833-3912df9a3374", 
      "area": 2.23, 
      "num_lifts": 5, 
      "source": "jsons/ski_area_elevations//asia-latest.json", 
      "min_elev": 264, 
      "cumarea": 9402.590456624594
    }, 
    {
      "max_elev": 884, 
      "uid": "0f5a7d73-c409-4d0e-9e92-6a98d8860f29", 
      "area": 1.81, 
      "num_lifts": 1, 
      "source": "jsons/ski_area_elevations//asia-latest.json", 
      "min_elev": 857, 
      "cumarea": 9397.200668374218
    }, 
    {
      "max_elev": 883, 
      "uid": "f8692144-1019-4f89-b06a-1aefb5ec46e5", 
      "area": 1.8, 
      "num_lifts": 1, 
      "source": "jsons/ski_area_elevations//europe-latest.json", 
      "min_elev": 855, 
      "cumarea": 9399.78845503912
    }
  ], 
  "end_x": 9403.89131141637, 
  "num": 1070, 
  "zoom": 11, 
  "start_x": 9395.110834001414
}