{
  "shown": [
    {
      "max_elev": 373, 
      "uid": "6ed586e5-fa10-43f1-a7ab-8f7a1444969c", 
      "area": 2.12, 
      "num_lifts": 14, 
      "source": "jsons/ski_area_elevations//europe-latest.json", 
      "min_elev": 227, 
      "cumarea": 14461.753375296648
    }, 
    {
      "max_elev": 373, 
      "uid": "f618ad87-4c7c-4741-a94b-84fa9d53417f", 
      "area": 1.86, 
      "num_lifts": 4, 
      "source": "jsons/ski_area_elevations//north-america-latest.json", 
      "min_elev": 313, 
      "cumarea": 14464.373951784373
    }, 
    {
      "max_elev": 373, 
      "uid": "dc9ca817-46ec-4a9f-9bee-2c3c934b1d8c", 
      "area": 1.81, 
      "num_lifts": 1, 
      "source": "jsons/ski_area_elevations//asia-latest.json", 
      "min_elev": 291, 
      "cumarea": 14466.96727862965
    }, 
    {
      "max_elev": 373, 
      "uid": "b2a60e0e-9e88-4b0c-ab56-56242db37ccf", 
      "area": 1.81, 
      "num_lifts": 1, 
      "source": "jsons/ski_area_elevations//asia-latest.json", 
      "min_elev": 317, 
      "cumarea": 14469.560605474928
    }
  ], 
  "end_x": 14470.226779845167, 
  "num": 1647, 
  "zoom": 11, 
  "start_x": 14461.446302430213
}