{
  "shown": [
    {
      "max_elev": 1768, 
      "uid": "e4f28b3d-7e85-47a5-8b9a-f6b42d349dbd", 
      "area": 2.6, 
      "num_lifts": 13, 
      "source": "jsons/ski_area_elevations//europe-latest.json", 
      "min_elev": 1330, 
      "cumarea": 4029.664406850528
    }, 
    {
      "max_elev": 1769, 
      "uid": "aaf618a1-25d2-4dc0-9968-9c52be26319e", 
      "area": 2.3, 
      "num_lifts": 6, 
      "source": "jsons/ski_area_elevations//europe-latest.json", 
      "min_elev": 839, 
      "cumarea": 4024.0937097664105
    }, 
    {
      "max_elev": 1769, 
      "uid": "4db4cf43-766b-421a-bfb6-83c7ac1f4ef4", 
      "area": 1.85, 
      "num_lifts": 1, 
      "source": "jsons/ski_area_elevations//europe-latest.json", 
      "min_elev": 975, 
      "cumarea": 4026.7088954055007
    }
  ], 
  "end_x": 4030.239133464157, 
  "num": 458, 
  "zoom": 11, 
  "start_x": 4021.4586560492025
}