{
  "shown": [
    {
      "max_elev": 1188, 
      "uid": "cc9ee629-fc71-4057-a209-50f5ee36bc00", 
      "area": 2.27, 
      "num_lifts": 7, 
      "source": "jsons/ski_area_elevations//europe-latest.json", 
      "min_elev": 1035, 
      "cumarea": 7099.258227427174
    }, 
    {
      "max_elev": 1190, 
      "uid": "803d3970-1e75-4f01-92a4-e97372870535", 
      "area": 2.18, 
      "num_lifts": 9, 
      "source": "jsons/ski_area_elevations//europe-latest.json", 
      "min_elev": 966, 
      "cumarea": 7096.43844759568
    }, 
    {
      "max_elev": 1188, 
      "uid": "8ef188c4-c9d2-4be5-ac3a-3c4ed8e82dae", 
      "area": 1.9000000000000001, 
      "num_lifts": 2, 
      "source": "jsons/ski_area_elevations//europe-latest.json", 
      "min_elev": 672, 
      "cumarea": 7101.900081313346
    }
  ], 
  "end_x": 7103.406228698264, 
  "num": 808, 
  "zoom": 11, 
  "start_x": 7094.62575128331
}