{
  "shown": [
    {
      "max_elev": 1083, 
      "uid": "9c3aab07-a889-41fc-9553-55e0e8e2dc25", 
      "area": 5.25, 
      "num_lifts": 87, 
      "source": "jsons/ski_area_elevations//europe-latest.json", 
      "min_elev": 604, 
      "cumarea": 7795.669161543993
    }, 
    {
      "max_elev": 1085, 
      "uid": "a4c2cc6b-ea62-47d4-8a37-d328dac43b67", 
      "area": 1.95, 
      "num_lifts": 2, 
      "source": "jsons/ski_area_elevations//europe-latest.json", 
      "min_elev": 845, 
      "cumarea": 7789.401167895769
    }, 
    {
      "max_elev": 1085, 
      "uid": "3778c5d9-2ce7-41d2-a21d-354bad301040", 
      "area": 1.84, 
      "num_lifts": 3, 
      "source": "jsons/ski_area_elevations//europe-latest.json", 
      "min_elev": 1046, 
      "cumarea": 7792.01093346739
    }
  ], 
  "end_x": 7797.063944479677, 
  "num": 887, 
  "zoom": 11, 
  "start_x": 7788.283467064723
}