{
  "shown": [
    {
      "max_elev": 899, 
      "uid": "2fe0f65f-1831-4baa-8809-0b8c74e420f6", 
      "area": 2.13, 
      "num_lifts": 3, 
      "source": "jsons/ski_area_elevations//europe-latest.json", 
      "min_elev": 789, 
      "cumarea": 9268.213208991783
    }, 
    {
      "max_elev": 898, 
      "uid": "b95d4765-70a0-4841-9ac0-ebaa39ab59d8", 
      "area": 2.06, 
      "num_lifts": 3, 
      "source": "jsons/ski_area_elevations//europe-latest.json", 
      "min_elev": 737, 
      "cumarea": 9270.935914974585
    }
  ], 
  "end_x": 9272.18415019205, 
  "num": 2111, 
  "zoom": 12, 
  "start_x": 9267.793911484572
}