{
  "shown": [
    {
      "max_elev": 49, 
      "uid": "912cfd4a-3459-4c4d-b33a-769675225cbe", 
      "area": 1.81, 
      "num_lifts": 1, 
      "source": "jsons/ski_area_elevations//europe-latest.json", 
      "min_elev": 34, 
      "cumarea": 17491.37081426255
    }, 
    {
      "max_elev": 49, 
      "uid": "67bae832-9c58-4acf-b190-6f74ce84dcd8", 
      "area": 1.81, 
      "num_lifts": 1, 
      "source": "jsons/ski_area_elevations//europe-latest.json", 
      "min_elev": 17, 
      "cumarea": 17493.96414110783
    }
  ], 
  "end_x": 17495.101249297026, 
  "num": 3984, 
  "zoom": 12, 
  "start_x": 17490.711010589548
}