{
  "shown": [
    {
      "max_elev": 38, 
      "uid": "efbac673-05f7-4cb2-9eee-2b99a88bcccf", 
      "area": 1.8, 
      "num_lifts": 1, 
      "source": "jsons/ski_area_elevations//europe-latest.json", 
      "min_elev": 14, 
      "cumarea": 17619.15275988429
    }, 
    {
      "max_elev": 38, 
      "uid": "1adaee5a-fcca-4a88-b823-4169d25e7b1a", 
      "area": 1.8, 
      "num_lifts": 1, 
      "source": "jsons/ski_area_elevations//europe-latest.json", 
      "min_elev": 38, 
      "cumarea": 17621.740546549194
    }
  ], 
  "end_x": 17622.418171813864, 
  "num": 4013, 
  "zoom": 12, 
  "start_x": 17618.027933106387
}